AUTHORS.rst
CONTRIBUTING.rst
HISTORY.rst
LICENSE
MANIFEST.in
README.rst
setup.cfg
setup.py
docs/Makefile
docs/authors.rst
docs/conf.py
docs/contributing.rst
docs/history.rst
docs/index.rst
docs/installation.rst
docs/make.bat
docs/readme.rst
docs/usage.rst
lcubo_helpers/__init__.py
lcubo_helpers/cli.py
lcubo_helpers/rotate.py
lcubo_helpers.egg-info/PKG-INFO
lcubo_helpers.egg-info/SOURCES.txt
lcubo_helpers.egg-info/dependency_links.txt
lcubo_helpers.egg-info/entry_points.txt
lcubo_helpers.egg-info/not-zip-safe
lcubo_helpers.egg-info/requires.txt
lcubo_helpers.egg-info/top_level.txt
tests/__init__.py
tests/test_lcubo_helpers.py