Metadata-Version: 1.1
Name: lcubo-helpers
Version: 0.1.4
Summary: some functions and classes I copy paste in several projects. this is a kitten saver
Home-page: https://github.com/llazzaro/lcubo_helpers
Author: Leonardo Lazzaro
Author-email: llazzaro@dc.uba.ar
License: MIT license
Keywords: lcubo_helpers
Platform: UNKNOWN
Classifier: Development Status :: 2 - Pre-Alpha
Classifier: Intended Audience :: Developers
Classifier: License :: OSI Approved :: MIT License
Classifier: Natural Language :: English
Classifier: Programming Language :: Python :: 2
Classifier: Programming Language :: Python :: 2.6
Classifier: Programming Language :: Python :: 2.7
Classifier: Programming Language :: Python :: 3
Classifier: Programming Language :: Python :: 3.3
Classifier: Programming Language :: Python :: 3.4
Classifier: Programming Language :: Python :: 3.5
